docs/pages/source/conf.py
examples/evalboards/MAX22215/basic_usage.py
examples/evalboards/MAX22215/brake_release_example.py
examples/evalboards/MAX22215/read_all_register_and_fields.py
examples/evalboards/MAX22216/datalogger_check.py
examples/evalboards/MAX22216/otp_burn.py
examples/evalboards/MAX22216/plunger_move.py
examples/evalboards/MAX22216/ramdebug.py
examples/evalboards/TMC2100/register_dump.py
examples/evalboards/TMC2100/rotate_demo.py
examples/evalboards/TMC2130/register_dump.py
examples/evalboards/TMC2130/rotate_demo.py
examples/evalboards/TMC2160/register_dump.py
examples/evalboards/TMC2160/rotate_demo.py
examples/evalboards/TMC2208/register_dump.py
examples/evalboards/TMC2208/rotate_demo.py
examples/evalboards/TMC2209/register_dump.py
examples/evalboards/TMC2209/rotate_demo.py
examples/evalboards/TMC2224/register_dump.py
examples/evalboards/TMC2224/rotate_demo.py
examples/evalboards/TMC2225/register_dump.py
examples/evalboards/TMC2225/rotate_demo.py
examples/evalboards/TMC2240/register_dump.py
examples/evalboards/TMC2240/rotate_demo.py
examples/evalboards/TMC2241/basic_usage.py
examples/evalboards/TMC2241/read_all_register.py
examples/evalboards/TMC2241/read_all_register_and_fields.py
examples/evalboards/TMC2262/basic_usage.py
examples/evalboards/TMC2262/basic_usage_microstep.py
examples/evalboards/TMC2262/read_all_register_and_fields.py
examples/evalboards/TMC2300/register_dump.py
examples/evalboards/TMC2300/rotate_demo.py
examples/evalboards/TMC2590/register_dump.py
examples/evalboards/TMC2590/rotate_demo.py
examples/evalboards/TMC2660/register_dump.py
examples/evalboards/TMC2660/rotate_demo.py
examples/evalboards/TMC4361/TMC4331_eval_TMC2130_eval_rotateDemo.py
examples/evalboards/TMC4361/register_dump.py
examples/evalboards/TMC4671/TMC4671_eval_BLDC_ABN_encoder.py
examples/evalboards/TMC4671/TMC4671_eval_BLDC_ABN_encoder_offset_estimation.py
examples/evalboards/TMC4671/TMC4671_eval_BLDC_open_loop.py
pytrinamic-0.2.20.dist-info/licenses/LICENSE
pytrinamic-0.2.20.dist-info/METADATA
pytrinamic-0.2.20.dist-info/WHEEL
pytrinamic-0.2.20.dist-info/entry_points.txt
pytrinamic-0.2.20.dist-info/top_level.txt
pytrinamic-0.2.20.dist-info/RECORD
