Metadata-Version: 2.4
Name: pytrinamic
Version: 0.2.20
Summary: TRINAMIC's Python Technology Access Package.
Author-email: ADI Trinamic Software Team <tmc_info@trinamic.com>
License: MIT
Project-URL: Homepage, https://github.com/analogdevicesinc/pytrinamic
Project-URL: Issues, https://github.com/analogdevicesinc/pytrinamic/issues
Classifier: Programming Language :: Python :: 3
Classifier: Intended Audience :: Developers
Classifier: Natural Language :: English
Classifier: License :: OSI Approved :: MIT License
Classifier: Operating System :: OS Independent
Requires-Python: >=3.7
License-File: LICENSE
Requires-Dist: python-can>=3
Requires-Dist: canopen
Requires-Dist: pyserial>=3
Requires-Dist: IntelHex>=2.3
Dynamic: license-file
